pokesage/__init__.py
pokesage/battle/__init__.py
pokesage/battle/battle.py
pokesage/battle/choices.py
pokesage/battle/pokemon.py
pokesage/battle/state.py
pokesage/battle/utilities.py
pokesage/connectors/__init__.py
pokesage/connectors/abstractconnector.py
pokesage/connectors/simulatorconnector.py
pokesage/connectors/websocketconnector.py
pokesage/processors/__init__.py
pokesage/processors/abstractprocessor.py
pokesage/processors/showdownprocessor.py
pokesage/sages/__init__.py
pokesage/sages/abstractsage.py
pokesage/sages/defaultsage.py
pokesage/sages/randomsage.py
pokesage/scripts/__init__.py
pokesage/scripts/api.py
pokesage/scripts/cli.py
pokesage-0.3.0.dist-info/LICENSE
pokesage-0.3.0.dist-info/METADATA
pokesage-0.3.0.dist-info/WHEEL
pokesage-0.3.0.dist-info/RECORD
