Metadata-Version: 2.1
Name: pokesage
Version: 0.3.0
Summary: Pokemon Playing AI training tools built with a modern, async, type-hinting stack
Home-page: https://github.com/trevorWieland/pokesage
License: MIT
Author: Trevor Wieland
Author-email: trevor_wieland@mac.com
Requires-Python: >=3.9,<3.13
Classifier: License :: OSI Approved :: MIT License
Classifier: Programming Language :: Python :: 3
Classifier: Programming Language :: Python :: 3.9
Classifier: Programming Language :: Python :: 3.10
Classifier: Programming Language :: Python :: 3.11
Requires-Dist: aiohttp (==3.9.0b0)
Requires-Dist: beartype (>=0.16.2,<0.17.0)
Requires-Dist: poketypes (>=0.2.1,<0.3.0)
Requires-Dist: pydantic (>=2.4.2,<3.0.0)
Requires-Dist: tqdm (>=4.66.1,<5.0.0)
Project-URL: Documentation, https://trevorwieland.github.io/pokesage/
Project-URL: Repository, https://github.com/trevorWieland/pokesage
